asyncprawcore-stubs/__init__.pyi
asyncprawcore-stubs/auth.pyi
asyncprawcore-stubs/codes.pyi
asyncprawcore-stubs/const.pyi
asyncprawcore-stubs/exceptions.pyi
asyncprawcore-stubs/rate_limit.pyi
asyncprawcore-stubs/requestor.pyi
asyncprawcore-stubs/sessions.pyi
asyncprawcore-stubs/util.pyi
asyncprawcore_stubs-0.0.1.dist-info/LICENSE
asyncprawcore_stubs-0.0.1.dist-info/METADATA
asyncprawcore_stubs-0.0.1.dist-info/WHEEL
asyncprawcore_stubs-0.0.1.dist-info/RECORD
